jsa/__init__.py
jsa/client/apis/apis_request_builder.py
jsa/client/apis/beta/acs/acs_request_builder.py
jsa/client/apis/beta/acs/v1/item/with_client_item_request_builder.py
jsa/client/apis/beta/acs/v1/v1_request_builder.py
jsa/client/apis/beta/beta_request_builder.py
jsa/client/apis/organizations/organizations_request_builder.py
jsa/client/apis/organizations/v1/item/authentication_policy/authentication_policy_request_builder.py
jsa/client/apis/organizations/v1/item/v1_item_request_builder.py
jsa/client/apis/organizations/v1/v1_request_builder.py
jsa/client/apis/service_accounts/service_accounts_request_builder.py
jsa/client/apis/service_accounts/v1/item/reset_secret/reset_secret_request_builder.py
jsa/client/apis/service_accounts/v1/item/v1_item_request_builder.py
jsa/client/apis/service_accounts/v1/v1_request_builder.py
jsa/client/kiota-lock.json
jsa/client/models/acs_client_request_data.py
jsa/client/models/acs_client_response_data.py
jsa/client/models/authentication_factors.py
jsa/client/models/authentication_policy.py
jsa/client/models/error.py
jsa/client/models/otp.py
jsa/client/models/red_hat_error_representation.py
jsa/client/models/red_hat_error_representation_error.py
jsa/client/models/service_account_create_request_data.py
jsa/client/models/service_account_data.py
jsa/client/models/service_account_request_data.py
jsa/client/models/validation_exception_data.py
jsa/client/models/validation_exception_data_fields.py
jsa/client/service_account_client.py
jsa-0.6.0.dist-info/METADATA
jsa-0.6.0.dist-info/WHEEL
jsa-0.6.0.dist-info/RECORD
